afsapi/__init__.py
afsapi/api.py
afsapi/exceptions.py
afsapi/models.py
afsapi/throttler.py
afsapi/utils.py
afsapi/version.py
afsapi-0.2.8.dist-info/LICENSE
afsapi-0.2.8.dist-info/METADATA
afsapi-0.2.8.dist-info/WHEEL
afsapi-0.2.8.dist-info/top_level.txt
afsapi-0.2.8.dist-info/RECORD
