Metadata-Version: 2.1
Name: afsapi
Version: 0.2.8
Summary: Asynchronous Implementation of the Frontier Silicon API
Home-page: https://github.com/zhelev/python-afsapi.git
Author: Krasimir Zhelev
Author-email: krasimir.zhelev@gmail.com
License: Apache License 2.0
Classifier: Intended Audience :: Developers
Classifier: License :: OSI Approved :: Apache Software License
Classifier: Operating System :: OS Independent
Classifier: Programming Language :: Python :: 3
Classifier: Programming Language :: Python :: 3.0
Classifier: Programming Language :: Python :: 3.1
Classifier: Programming Language :: Python :: 3.2
Classifier: Programming Language :: Python :: 3.3
Classifier: Programming Language :: Python :: 3.4
Classifier: Programming Language :: Python :: 3.5
Classifier: Programming Language :: Python :: 3.6
Classifier: Topic :: Software Development :: Libraries
Requires-Python: >=3.7
License-File: LICENSE
Requires-Dist: aiohttp (<4,>=3.3.2)
